sarssm/__init__.py
sarssm/common.py
sarssm/conversion/__init__.py
sarssm/conversion/hallikainen1985.py
sarssm/conversion/topp1980.py
sarssm/conversion/ulaby1987.py
sarssm/conversion/ulaby1987_plots.py
sarssm/decomposition/__init__.py
sarssm/decomposition/cloude1996.py
sarssm/insar/__init__.py
sarssm/insar/dezan2014.py
sarssm/insar/dezan2014inversion.py
sarssm/polsar/__init__.py
sarssm/polsar/hajnsek2003.py
sarssm/polsar/hajnsek2003_plots.py
sarssm-1.0.0.dist-info/licenses/LICENSE
sarssm-1.0.0.dist-info/METADATA
sarssm-1.0.0.dist-info/WHEEL
sarssm-1.0.0.dist-info/top_level.txt
sarssm-1.0.0.dist-info/RECORD
