Metadata-Version: 2.4
Name: sarssm
Version: 1.0.0
Summary: Selected algorithms for surface soil moisture (SSM) estimation from SAR data
Author-email: Nikita Basargin <nikita.basargin@dlr.de>
License: MIT
Requires-Python: >=3.10
License-File: LICENSE
Requires-Dist: numpy
Requires-Dist: torch
Requires-Dist: scipy
Requires-Dist: matplotlib
Dynamic: license-file
